{
    "executive_summary": "Coca-Cola is undergoing a leadership transition with a new CEO, Henrique Braun, emphasizing digital growth and innovation. Recent Q4 results showed mixed performance with revenue misses but EPS beats. Analysts remain largely positive, with price target increases, while a class-action lawsuit regarding animal welfare and a new mini-can offering present mixed implications.",
    "market_sentiment_verdict": "Neutral",
    "global_macro_context": {
        "macro_summary": "Global markets are influenced by ongoing geopolitical tensions and the potential for AI disruption across various sectors. While some economies show resilience and positive earnings, concerns about inflation and interest rate policies persist, creating a cautious market environment. Geopolitical events continue to add uncertainty, impacting commodity prices and global trade dynamics."
    },
    "top_news_developments": [
        {
            "headline": "Coca-Cola Leadership Shift Puts Digital Growth And Valuation In Focus",
            "source": "Simply Wall St.",
            "date": "2026-02-17",
            "sentiment": "Positive",
            "implication": "New CEO and focus on digital growth could drive future valuation increases."
        },
        {
            "headline": "Fairlife, Coca-Cola Class Action Over Alleged Cow Abuse Trimmed",
            "source": "Bloomberg Law",
            "date": "2026-02-16",
            "sentiment": "Negative",
            "implication": "While some claims were dismissed, remaining lawsuits could still impact brand reputation and incur legal costs."
        },
        {
            "headline": "Coca-Cola FEMSA Prices MX$10 Billion Bond Offering",
            "source": "TipRanks",
            "date": "2026-02-13",
            "sentiment": "Positive",
            "implication": "Successful debt issuance provides financial flexibility and indicates investor confidence in the company's prospects."
        },
        {
            "headline": "Coca-Cola trumpets its performance in China",
            "source": "China Daily - Global Edition",
            "date": "2026-02-13",
            "sentiment": "Positive",
            "implication": "Strong performance in China highlights a key growth market and positive regional strategy execution."
        },
        {
            "headline": "Coca-Cola makes a surprising change to its products",
            "source": "The Sun",
            "date": "2026-02-13",
            "sentiment": "Positive",
            "implication": "Introduction of mini-cans offers consumers more choice and affordability, potentially boosting sales and market appeal."
        }
    ],
    "key_risks": [
        "Potential negative impact from ongoing class-action lawsuits regarding animal welfare.",
        "Slowing revenue growth in certain segments and increased competition in the beverage market.",
        "Execution risk associated with the new CEO's digital growth and innovation strategy."
    ]
}